ferno.py
ferno-1.0.1.data/scripts/ferno.py
ferno-1.0.1.dist-info/METADATA
ferno-1.0.1.dist-info/WHEEL
ferno-1.0.1.dist-info/entry_points.txt
ferno-1.0.1.dist-info/top_level.txt
ferno-1.0.1.dist-info/RECORD
