Metadata-Version: 2.4
Name: ferno
Version: 1.0.1
Requires-Dist: textual
Dynamic: requires-dist
